schemander.py
schemander-0.0.7.dist-info/LICENSE
schemander-0.0.7.dist-info/METADATA
schemander-0.0.7.dist-info/WHEEL
schemander-0.0.7.dist-info/top_level.txt
schemander-0.0.7.dist-info/RECORD
