Metadata-Version: 2.1
Name: schemander
Version: 0.0.7
Summary: A single file schema validator for dictionaries.
Author-email: Miguel Alejandro Salgado Zapien <ekiim@ekiim.xyz>
License: GPL-2.0
Project-URL: Homepage, https://schemander.ekiim.xyz
Project-URL: Source, https://github.com/ekiim/schemander
Classifier: Development Status :: 2 - Pre-Alpha
Classifier: License :: OSI Approved :: GNU General Public License v2 (GPLv2)
Classifier: Programming Language :: Python :: 3.11
Requires-Python: >=3.11
License-File: LICENSE
Requires-Dist: PyJWT
Requires-Dist: phonenumbers (>=3.12.32)
Provides-Extra: dev
Requires-Dist: black ; extra == 'dev'
Requires-Dist: build ; extra == 'dev'
Requires-Dist: mypy ; extra == 'dev'
Requires-Dist: pytest ; extra == 'dev'
Requires-Dist: pytest-cov ; extra == 'dev'
Requires-Dist: python-lsp-server[all] ; extra == 'dev'
Requires-Dist: types-PyJWT ; extra == 'dev'
Requires-Dist: twine ; extra == 'dev'
